{
  "sport": "baseball",
  "league": "mlb",
  "date": "20260716",
  "count": 1,
  "games": [
    {
      "id": "401816143",
      "name": "New York Mets at Philadelphia Phillies",
      "shortName": "NYM @ PHI",
      "date": "2026-07-16T23:00Z",
      "state": "pre",
      "status": "7/16 - 7:00 PM EDT",
      "completed": false,
      "home": {
        "id": "22",
        "abbr": "PHI",
        "name": "Philadelphia Phillies",
        "score": "0"
      },
      "away": {
        "id": "21",
        "abbr": "NYM",
        "name": "New York Mets",
        "score": "0"
      }
    }
  ]
}
